{
    "etag": "\"j6xRRd8dTPVVptg711_CSPADRfg\/ZYXvchCMwPg2urJ-bXjNzQorFo0\"",
    "id": "4m4UtujnpQU",
    "kind": "youtube#video",
    "snippet": {
        "categoryId": "20",
        "channelId": "UCo_IB5145EVNcf8hw1Kku7w",
        "channelTitle": "The Game Theorists",
        "defaultAudioLanguage": "en-US",
        "defaultLanguage": null,
        "description": "MatPat Gone WILD! | Breath of the Wild \u25ba\u25ba https:\/\/goo.gl\/TfSMKc\nWatch MORE on the GTLive Channel! \u25ba\u25ba http:\/\/bit.ly\/1LkSBnz \nUSE: #GTLIVE and @matpatgt to send us comments & questions!\n\nToday, we're playing an online game called Idiots.Win! Basically, we have to summon our inner idiot as we view a list of Internet Searches and guess which option is the most searched! Join us for this early (and goofy) livestream!\n\nSubscribe & hang out with us every day! \u25ba\u25ba http:\/\/bit.ly\/1Oo7KH9\nFollow us on Twitter at @MatPatGT and #GTLive\n\nMore GTLive Videos:\nMissed Part 3 of FNAC 3? Watch it Now! \u25ba http:\/\/bit.ly\/2o0Mldr\nMissed Part 2 of FNAC 3? Watch it! \u25ba\u25ba https:\/\/goo.gl\/oqsre8\nMissed Part 1 of FNAC 3? Watch it! \u25ba\u25ba http:\/\/bit.ly\/2nNax1V\nStanley's Start of Something Terrible! \u25ba http:\/\/bit.ly\/2kn7P1E\nPlayDate from HELL! | Emily Wants to Play \u25ba https:\/\/goo.gl\/8m8cXn\nCUT IT OUT! | Snipperclips \u25ba\u25bahttps:\/\/goo.gl\/DcfDQi\n\nSad Puppet is Sad! - FNAC Part 1 \u25ba\u25ba http:\/\/bit.ly\/1U8Xs0I\n\nDon't have much time but need a quick fix? Check out some of our highlight episodes for hilarious moments from our live streams. Here are a few to get you started.\n\nHiLite: FNAF Theorists Surprised By Scott! \u25ba http:\/\/bit.ly\/1Jrlm3i\nHiLite: Shocked by Man Muscle! \u25ba\u25ba http:\/\/bit.ly\/1VbxgiC\nHiLite: Until Dawn's SPOOPTACULAR!!! \u25ba http:\/\/bit.ly\/1WSF5uq\n\nThanks to David Keller for allowing us use of his sound FX:\nhttp:\/\/consumingfireartisticcreations.weebly.com\/",
        "liveBroadcastContent": "none",
        "publishedAt": "2017-03-27T16:33:44.000Z",
        "tags": [
            "google autocomplete",
            "idiots.win",
            "Google Feud",
            "google",
            "google feud game",
            "google game",
            "google feud jacksepticeye",
            "google autocomplete game",
            "auto complete answers",
            "idiots win",
            "trivia",
            "answers",
            "lets play",
            "reaction",
            "react to",
            "fill in the blank",
            "auto fill",
            "fun",
            "funny",
            "weird",
            "silly",
            "free game",
            "online game",
            "survey says",
            "gtlive",
            "gt live",
            "gtlive matpat",
            "game theory",
            "game theory live",
            "game theory matpat",
            "matpat fan game",
            "autocomplete answers"
        ],
        "title": "GTLive: IDIOTS WIN! | Google Autocomplete",
        "thumbnails": {
            "default": {
                "height": 90,
                "url": "https:\/\/i.ytimg.com\/vi\/4m4UtujnpQU\/default.jpg",
                "width": 120
            },
            "medium": {
                "height": 180,
                "url": "https:\/\/i.ytimg.com\/vi\/4m4UtujnpQU\/mqdefault.jpg",
                "width": 320
            },
            "high": {
                "height": 360,
                "url": "https:\/\/i.ytimg.com\/vi\/4m4UtujnpQU\/hqdefault.jpg",
                "width": 480
            }
        },
        "localized": {
            "description": "MatPat Gone WILD! | Breath of the Wild \u25ba\u25ba https:\/\/goo.gl\/TfSMKc\nWatch MORE on the GTLive Channel! \u25ba\u25ba http:\/\/bit.ly\/1LkSBnz \nUSE: #GTLIVE and @matpatgt to send us comments & questions!\n\nToday, we're playing an online game called Idiots.Win! Basically, we have to summon our inner idiot as we view a list of Internet Searches and guess which option is the most searched! Join us for this early (and goofy) livestream!\n\nSubscribe & hang out with us every day! \u25ba\u25ba http:\/\/bit.ly\/1Oo7KH9\nFollow us on Twitter at @MatPatGT and #GTLive\n\nMore GTLive Videos:\nMissed Part 3 of FNAC 3? Watch it Now! \u25ba http:\/\/bit.ly\/2o0Mldr\nMissed Part 2 of FNAC 3? Watch it! \u25ba\u25ba https:\/\/goo.gl\/oqsre8\nMissed Part 1 of FNAC 3? Watch it! \u25ba\u25ba http:\/\/bit.ly\/2nNax1V\nStanley's Start of Something Terrible! \u25ba http:\/\/bit.ly\/2kn7P1E\nPlayDate from HELL! | Emily Wants to Play \u25ba https:\/\/goo.gl\/8m8cXn\nCUT IT OUT! | Snipperclips \u25ba\u25bahttps:\/\/goo.gl\/DcfDQi\n\nSad Puppet is Sad! - FNAC Part 1 \u25ba\u25ba http:\/\/bit.ly\/1U8Xs0I\n\nDon't have much time but need a quick fix? Check out some of our highlight episodes for hilarious moments from our live streams. Here are a few to get you started.\n\nHiLite: FNAF Theorists Surprised By Scott! \u25ba http:\/\/bit.ly\/1Jrlm3i\nHiLite: Shocked by Man Muscle! \u25ba\u25ba http:\/\/bit.ly\/1VbxgiC\nHiLite: Until Dawn's SPOOPTACULAR!!! \u25ba http:\/\/bit.ly\/1WSF5uq\n\nThanks to David Keller for allowing us use of his sound FX:\nhttp:\/\/consumingfireartisticcreations.weebly.com\/",
            "title": "GTLive: IDIOTS WIN! | Google Autocomplete"
        }
    },
    "liveStreamingDetails": {
        "activeLiveChatId": null,
        "actualEndTime": "2017-03-27T20:23:49.000Z",
        "actualStartTime": "2017-03-27T19:02:47.151Z",
        "concurrentViewers": null,
        "scheduledEndTime": null,
        "scheduledStartTime": "2017-03-27T19:00:00.000Z"
    }
}