{
    "etag": "\"j6xRRd8dTPVVptg711_CSPADRfg\/qrF2ryLhhlN9kN20OlyTC23vPUs\"",
    "id": "a8kfB09WA0Q",
    "kind": "youtube#video",
    "snippet": {
        "categoryId": "24",
        "channelId": "UCo_IB5145EVNcf8hw1Kku7w",
        "channelTitle": "The Game Theorists",
        "defaultAudioLanguage": "en",
        "defaultLanguage": null,
        "description": "Can We ESCAPE?! | A Way Out \u25ba https:\/\/bit.ly\/2I5Wgfh\nBaby 101 | Parenting Style Quiz \u25ba https:\/\/bit.ly\/2jJcH2G\nClick Here for More GTLive Action! \u25ba\u25ba http:\/\/bit.ly\/1Oo7KH9\n\nToday Theorists, we are diving deep into the world of online quizzes. Do we know that obscure fact? What type of box are we? Who's that Pokemon? Let see if we can get it right!\n\nSubscribe & hang out with us every day! \u25ba\u25ba http:\/\/bit.ly\/1Oo7KH9\nFollow us on Twitter at @MatPatGT and #GTLive\n\nMore GTLive Videos: \nBe SMART or DIE! | Trivia Murder Party \u25ba\u25ba https:\/\/bit.ly\/2Kb2JSF\nThe Impossible Quiz: The FAIL Begins \u25ba\u25ba https:\/\/bit.ly\/2wqwGw2\nULTIMATE RELATIONSHIP GOALS \u25ba http:\/\/bit.ly\/2HwDidE\nGetting INAPPROPRIATE with You! \u25ba\u25ba https:\/\/bit.ly\/2rzRGe5\nTHIS IS THE WEIRDEST QUIZ EVER!! \u25ba\u25ba https:\/\/bit.ly\/2G2DpvD\nWe FAILED This Test! Will YOU? \u25ba https:\/\/bit.ly\/2IcznCU",
        "liveBroadcastContent": "none",
        "publishedAt": "2018-05-10T20:59:02.000Z",
        "tags": [
            "quiz",
            "quizzes",
            "impossible",
            "impossible quiz",
            "trivia",
            "online quiz",
            "buzzfeed quiz",
            "test",
            "game theorists",
            "trivia game",
            "sporcle",
            "sporcle live",
            "sporcle trivia",
            "gtlive",
            "matpat",
            "gtlive quiz",
            "matpat quiz",
            "gtlive impossible",
            "gtlive challenges",
            "rage",
            "fail",
            "challenge",
            "fails",
            "can you pass",
            "can you answer",
            "brain teasers with answers",
            "riddles with answers",
            "test your brain"
        ],
        "title": "GTLive: Give Me Your WORST! |  Fan Submitted Quiz Challenge (Sporcle)",
        "thumbnails": {
            "default": {
                "height": 90,
                "url": "https:\/\/i.ytimg.com\/vi\/a8kfB09WA0Q\/default.jpg",
                "width": 120
            },
            "medium": {
                "height": 180,
                "url": "https:\/\/i.ytimg.com\/vi\/a8kfB09WA0Q\/mqdefault.jpg",
                "width": 320
            },
            "high": {
                "height": 360,
                "url": "https:\/\/i.ytimg.com\/vi\/a8kfB09WA0Q\/hqdefault.jpg",
                "width": 480
            }
        },
        "localized": {
            "description": "Can We ESCAPE?! | A Way Out \u25ba https:\/\/bit.ly\/2I5Wgfh\nBaby 101 | Parenting Style Quiz \u25ba https:\/\/bit.ly\/2jJcH2G\nClick Here for More GTLive Action! \u25ba\u25ba http:\/\/bit.ly\/1Oo7KH9\n\nToday Theorists, we are diving deep into the world of online quizzes. Do we know that obscure fact? What type of box are we? Who's that Pokemon? Let see if we can get it right!\n\nSubscribe & hang out with us every day! \u25ba\u25ba http:\/\/bit.ly\/1Oo7KH9\nFollow us on Twitter at @MatPatGT and #GTLive\n\nMore GTLive Videos: \nBe SMART or DIE! | Trivia Murder Party \u25ba\u25ba https:\/\/bit.ly\/2Kb2JSF\nThe Impossible Quiz: The FAIL Begins \u25ba\u25ba https:\/\/bit.ly\/2wqwGw2\nULTIMATE RELATIONSHIP GOALS \u25ba http:\/\/bit.ly\/2HwDidE\nGetting INAPPROPRIATE with You! \u25ba\u25ba https:\/\/bit.ly\/2rzRGe5\nTHIS IS THE WEIRDEST QUIZ EVER!! \u25ba\u25ba https:\/\/bit.ly\/2G2DpvD\nWe FAILED This Test! Will YOU? \u25ba https:\/\/bit.ly\/2IcznCU",
            "title": "GTLive: Give Me Your WORST! |  Fan Submitted Quiz Challenge (Sporcle)"
        }
    },
    "liveStreamingDetails": {
        "activeLiveChatId": null,
        "actualEndTime": "2018-05-11T00:17:56.000Z",
        "actualStartTime": "2018-05-10T23:07:33.237Z",
        "concurrentViewers": null,
        "scheduledEndTime": null,
        "scheduledStartTime": "2018-05-10T23:00:00.000Z"
    }
}