{
    "etag": "\"j6xRRd8dTPVVptg711_CSPADRfg\/tgKRkKA6h7hkjcewG9P3vR9E2wY\"",
    "id": "DSUmViwwGFo",
    "kind": "youtube#video",
    "snippet": {
        "categoryId": "20",
        "channelId": "UCAaegDUlb7doIKo0Rc1F08g",
        "channelTitle": "GTLive",
        "defaultAudioLanguage": "en-US",
        "defaultLanguage": null,
        "description": "Want MORE Mario Maker Streams?! \u25ba\u25ba http:\/\/bit.ly\/1jRUk9s\nMore Mario Highlights! \u25ba\u25ba http:\/\/bit.ly\/1ZiTgMq\nSubscribing to GLive? A Winning Move! \u25ba\u25bahttp:\/\/bit.ly\/1Oo7KH9 \n\nIn this Super Mario Maker Wednesday episode of GTLive, I try to \"speed run\" Mario Maker levels you've submitted to me in 10 lives or less. How did we do? You decide!\n\nFollow all the updates on new episodes of GTLive!\n\nSubscribe & hang out with us every day! \u25ba\u25bahttp:\/\/bit.ly\/1Oo7KH9\nFollow us on Twitter at @MatPatGT and #GTLive\n\nThanks so much to Thomas Torbergsen for editing the intro for GTLive and a whole bunch of the highlights episodes!",
        "liveBroadcastContent": "none",
        "publishedAt": "2015-10-09T16:05:08.000Z",
        "tags": [
            "mario",
            "Mario (Film Character)",
            "walkthrough",
            "mario maker",
            "let play",
            "playthrough",
            "Super Mario Bros. (Video Game)",
            "Super Mario Maker",
            "Mario Series (Video Game Series)",
            "game theory mario",
            "game theory",
            "Game Theory (Field Of Study)",
            "GTLive",
            "GT Live",
            "game theory live",
            "matpat",
            "matthew patrick"
        ],
        "title": "GTLive: Mario Maker Pro Tip FAIL! (COMPLETE)",
        "thumbnails": {
            "default": {
                "height": 90,
                "url": "https:\/\/i.ytimg.com\/vi\/DSUmViwwGFo\/default.jpg",
                "width": 120
            },
            "medium": {
                "height": 180,
                "url": "https:\/\/i.ytimg.com\/vi\/DSUmViwwGFo\/mqdefault.jpg",
                "width": 320
            },
            "high": {
                "height": 360,
                "url": "https:\/\/i.ytimg.com\/vi\/DSUmViwwGFo\/hqdefault.jpg",
                "width": 480
            },
            "standard": {
                "height": 480,
                "url": "https:\/\/i.ytimg.com\/vi\/DSUmViwwGFo\/sddefault.jpg",
                "width": 640
            },
            "maxres": {
                "height": 720,
                "url": "https:\/\/i.ytimg.com\/vi\/DSUmViwwGFo\/maxresdefault.jpg",
                "width": 1280
            }
        },
        "localized": {
            "description": "Want MORE Mario Maker Streams?! \u25ba\u25ba http:\/\/bit.ly\/1jRUk9s\nMore Mario Highlights! \u25ba\u25ba http:\/\/bit.ly\/1ZiTgMq\nSubscribing to GLive? A Winning Move! \u25ba\u25bahttp:\/\/bit.ly\/1Oo7KH9 \n\nIn this Super Mario Maker Wednesday episode of GTLive, I try to \"speed run\" Mario Maker levels you've submitted to me in 10 lives or less. How did we do? You decide!\n\nFollow all the updates on new episodes of GTLive!\n\nSubscribe & hang out with us every day! \u25ba\u25bahttp:\/\/bit.ly\/1Oo7KH9\nFollow us on Twitter at @MatPatGT and #GTLive\n\nThanks so much to Thomas Torbergsen for editing the intro for GTLive and a whole bunch of the highlights episodes!",
            "title": "GTLive: Mario Maker Pro Tip FAIL! (COMPLETE)"
        }
    },
    "topicDetails": {
        "relevantTopicIds": [
            "\/m\/0bzvm2",
            "\/m\/025zzc",
            "\/m\/0bzvm2",
            "\/m\/025zzc"
        ],
        "topicCategories": [
            "https:\/\/en.wikipedia.org\/wiki\/Video_game_culture",
            "https:\/\/en.wikipedia.org\/wiki\/Action_game"
        ],
        "topicIds": null
    }
}