{
    "etag": "\"j6xRRd8dTPVVptg711_CSPADRfg\/_NuIE7Sxqy6zSPcYR6LnXBWp7pY\"",
    "id": "KxDSJ30L8Ds",
    "kind": "youtube#video",
    "snippet": {
        "categoryId": "24",
        "channelId": "UCo_IB5145EVNcf8hw1Kku7w",
        "channelTitle": "The Game Theorists",
        "defaultAudioLanguage": "en",
        "defaultLanguage": null,
        "description": "Click Here for More GTLive Action! \u25ba\u25ba http:\/\/bit.ly\/1Oo7KH9\nWe Followed A NikkieTutorials Tutorial \u25ba https:\/\/bit.ly\/2EaTnbD\nTrying a Simply Nailogical Tutorial! \u25ba https:\/\/bit.ly\/2whuowE\n\nIt's time to paint some HAPPY TREES! Today Stephanie and I are following a Bob Ross painting tutorial. Let's see what kind of artistic masterpiece we can create!\n\n#BobRoss #BobRossTutorial #Painting #PaintingTutorial #FollowingABobRossPainting \n\nSubscribe & hang out with us every day! \u25ba\u25ba http:\/\/bit.ly\/1Oo7KH9\nFollow us on Twitter at @MatPatGT and #GTLive\n\nMore GTLive Videos: \nSWEET SURPRISE? | Ice Cream Challenge \u25ba\u25ba https:\/\/bit.ly\/2MHSo2j\nGood Mythical Morning Was WRONG!! \u25ba\u25ba https:\/\/bit.ly\/2CieC9G\nULTIMATE RELATIONSHIP GOALS \u25ba http:\/\/bit.ly\/2HwDidE\nCRAZY or CORRECT? Gender Prediction Tests \u25ba https:\/\/bit.ly\/2P4zdBm\nMake Me Happy Vine! \u25ba https:\/\/bit.ly\/2KWae0w",
        "liveBroadcastContent": "none",
        "publishedAt": "2018-10-09T18:54:26.000Z",
        "tags": [
            "bob ross",
            "painting bob ross",
            "bob ross jenna",
            "following a bob ross painting",
            "following bob ross",
            "jenna marbles bob ross",
            "simply nailogical bob ross",
            "bob ross episodes",
            "joy of painting",
            "painting",
            "painting tutorials",
            "tutorial",
            "bob ross song",
            "deadpool 2 bob ross",
            "bob ross meme",
            "bob painter",
            "deadpool bob ross",
            "bob ross deadpool",
            "joy of painting season 1",
            "bob ross asmr",
            "matpat",
            "happy trees",
            "gtlive",
            "game theorists",
            "gtlive bob ross",
            "matpat bob ross",
            "gtlive painting"
        ],
        "title": "GTLive: Following A Bob Ross Painting Tutorial - Are We ARTISTS?!",
        "thumbnails": {
            "default": {
                "height": 90,
                "url": "https:\/\/i.ytimg.com\/vi\/KxDSJ30L8Ds\/default.jpg",
                "width": 120
            },
            "medium": {
                "height": 180,
                "url": "https:\/\/i.ytimg.com\/vi\/KxDSJ30L8Ds\/mqdefault.jpg",
                "width": 320
            },
            "high": {
                "height": 360,
                "url": "https:\/\/i.ytimg.com\/vi\/KxDSJ30L8Ds\/hqdefault.jpg",
                "width": 480
            }
        },
        "localized": {
            "description": "Click Here for More GTLive Action! \u25ba\u25ba http:\/\/bit.ly\/1Oo7KH9\nWe Followed A NikkieTutorials Tutorial \u25ba https:\/\/bit.ly\/2EaTnbD\nTrying a Simply Nailogical Tutorial! \u25ba https:\/\/bit.ly\/2whuowE\n\nIt's time to paint some HAPPY TREES! Today Stephanie and I are following a Bob Ross painting tutorial. Let's see what kind of artistic masterpiece we can create!\n\n#BobRoss #BobRossTutorial #Painting #PaintingTutorial #FollowingABobRossPainting \n\nSubscribe & hang out with us every day! \u25ba\u25ba http:\/\/bit.ly\/1Oo7KH9\nFollow us on Twitter at @MatPatGT and #GTLive\n\nMore GTLive Videos: \nSWEET SURPRISE? | Ice Cream Challenge \u25ba\u25ba https:\/\/bit.ly\/2MHSo2j\nGood Mythical Morning Was WRONG!! \u25ba\u25ba https:\/\/bit.ly\/2CieC9G\nULTIMATE RELATIONSHIP GOALS \u25ba http:\/\/bit.ly\/2HwDidE\nCRAZY or CORRECT? Gender Prediction Tests \u25ba https:\/\/bit.ly\/2P4zdBm\nMake Me Happy Vine! \u25ba https:\/\/bit.ly\/2KWae0w",
            "title": "GTLive: Following A Bob Ross Painting Tutorial - Are We ARTISTS?!"
        }
    },
    "liveStreamingDetails": {
        "activeLiveChatId": null,
        "actualEndTime": "2018-10-10T00:31:01.000Z",
        "actualStartTime": "2018-10-09T23:02:28.998Z",
        "concurrentViewers": null,
        "scheduledEndTime": null,
        "scheduledStartTime": "2018-10-09T23:00:00.000Z"
    }
}