{
    "etag": "\"j6xRRd8dTPVVptg711_CSPADRfg\/I3bA7zYjVw3g0fMPa7lGyxOAZpY\"",
    "id": "SPBMJKdxH1Q",
    "kind": "youtube#video",
    "snippet": {
        "categoryId": "24",
        "channelId": "UCo_IB5145EVNcf8hw1Kku7w",
        "channelTitle": "The Game Theorists",
        "defaultAudioLanguage": "en",
        "defaultLanguage": null,
        "description": "Buy Merch Here: https:\/\/creatormash.com\/\nA BRAND NEW DAY in this DDLC Mod (Pt 2) \u25ba https:\/\/goo.gl\/322sHm\nFan-Submitted TRY NOT TO LAUGH! \u25ba\u25ba https:\/\/goo.gl\/6RP5aQ\nClick Here for More GTLive Action! \u25ba\u25ba http:\/\/bit.ly\/1Oo7KH9\n\nIt's Monday, and we're reacting to bad ads again! Chris spent a few hours finding the best of theworst infomercials out there, so get ready for some wacky stuff. Join Steph and I for what will surely be a hilarious day on GTLive!\n\nSubscribe & hang out with us every day! \u25ba\u25ba http:\/\/bit.ly\/1Oo7KH9\nFollow us on Twitter at @MatPatGT and #GTLive\n\nMore GTLive Videos:\nEveryone's a LIAR! | Hidden Agenda \u25ba https:\/\/goo.gl\/emHCCv\nNatsuki Is My WIFE? | DDLC Mod Part 2 \u25ba\u25ba https:\/\/goo.gl\/am6iRT\nENDLESS INSIDE! (Pt 2) \u25ba\u25ba https:\/\/goo.gl\/Qr5hRq\nAre YOU Smarter Than Us? | 94% Quiz \u25ba\u25ba https:\/\/goo.gl\/25SJQ4\nENDLESS INSIDE! (Pt 1) \u25ba\u25bahttps:\/\/goo.gl\/4Hpyn1\nWHAT'S NEW? | Hello Neighbor (Pt 1) \u25ba\u25ba http:\/\/bit.ly\/2o79kHB\nDuck Season's Final Ending \u25ba\u25ba http:\/\/bit.ly\/2A1m6wl\nTHE NEW RING IS MINE! | Shadow of War \u25ba\u25ba https:\/\/goo.gl\/bvKNKh\nI Google Myself! \u25ba\u25ba https:\/\/goo.gl\/uH25yg\n\nDon't have much time but need a quick fix? Check out some of our Must See Moments! Here Are a few to get You Started:\n\nWhy FNAF is Over! | TJoC: Story Mode (Pt.1) \u25ba https:\/\/goo.gl\/Bawy39\nWho's Your DADDY! | Dream Daddy \u25ba\u25ba https:\/\/goo.gl\/eJu12i\nNO RAGE HERE! | World's Easyest Game \u25ba\u25ba https:\/\/goo.gl\/Rc6UN3",
        "liveBroadcastContent": "none",
        "publishedAt": "2018-02-12T22:10:53.000Z",
        "tags": [
            "infomercial",
            "reaction",
            "try not to laugh",
            "shake weight",
            "oxiclean",
            "react",
            "funny infomercials",
            "billy mays",
            "shamwow",
            "try not to laugh challenge",
            "funny commercials",
            "react to",
            "commercial",
            "gtlive reacts",
            "try not to cringe",
            "cringe",
            "compilation",
            "fun",
            "funny",
            "infomercial challenge",
            "challenge",
            "gtlive",
            "infomercial reaction",
            "gt live",
            "try not to laugh gtlive",
            "super bowl commercial",
            "gtlive matpat",
            "gtlive try not to laugh",
            "sauna pants",
            "infomercial compilation"
        ],
        "title": "GTLive: TO BUY or NOT TO BUY? | MatPat REACTS to Infomercials!",
        "thumbnails": {
            "default": {
                "height": 90,
                "url": "https:\/\/i.ytimg.com\/vi\/SPBMJKdxH1Q\/default.jpg",
                "width": 120
            },
            "medium": {
                "height": 180,
                "url": "https:\/\/i.ytimg.com\/vi\/SPBMJKdxH1Q\/mqdefault.jpg",
                "width": 320
            },
            "high": {
                "height": 360,
                "url": "https:\/\/i.ytimg.com\/vi\/SPBMJKdxH1Q\/hqdefault.jpg",
                "width": 480
            }
        },
        "localized": {
            "description": "Buy Merch Here: https:\/\/creatormash.com\/\nA BRAND NEW DAY in this DDLC Mod (Pt 2) \u25ba https:\/\/goo.gl\/322sHm\nFan-Submitted TRY NOT TO LAUGH! \u25ba\u25ba https:\/\/goo.gl\/6RP5aQ\nClick Here for More GTLive Action! \u25ba\u25ba http:\/\/bit.ly\/1Oo7KH9\n\nIt's Monday, and we're reacting to bad ads again! Chris spent a few hours finding the best of theworst infomercials out there, so get ready for some wacky stuff. Join Steph and I for what will surely be a hilarious day on GTLive!\n\nSubscribe & hang out with us every day! \u25ba\u25ba http:\/\/bit.ly\/1Oo7KH9\nFollow us on Twitter at @MatPatGT and #GTLive\n\nMore GTLive Videos:\nEveryone's a LIAR! | Hidden Agenda \u25ba https:\/\/goo.gl\/emHCCv\nNatsuki Is My WIFE? | DDLC Mod Part 2 \u25ba\u25ba https:\/\/goo.gl\/am6iRT\nENDLESS INSIDE! (Pt 2) \u25ba\u25ba https:\/\/goo.gl\/Qr5hRq\nAre YOU Smarter Than Us? | 94% Quiz \u25ba\u25ba https:\/\/goo.gl\/25SJQ4\nENDLESS INSIDE! (Pt 1) \u25ba\u25bahttps:\/\/goo.gl\/4Hpyn1\nWHAT'S NEW? | Hello Neighbor (Pt 1) \u25ba\u25ba http:\/\/bit.ly\/2o79kHB\nDuck Season's Final Ending \u25ba\u25ba http:\/\/bit.ly\/2A1m6wl\nTHE NEW RING IS MINE! | Shadow of War \u25ba\u25ba https:\/\/goo.gl\/bvKNKh\nI Google Myself! \u25ba\u25ba https:\/\/goo.gl\/uH25yg\n\nDon't have much time but need a quick fix? Check out some of our Must See Moments! Here Are a few to get You Started:\n\nWhy FNAF is Over! | TJoC: Story Mode (Pt.1) \u25ba https:\/\/goo.gl\/Bawy39\nWho's Your DADDY! | Dream Daddy \u25ba\u25ba https:\/\/goo.gl\/eJu12i\nNO RAGE HERE! | World's Easyest Game \u25ba\u25ba https:\/\/goo.gl\/Rc6UN3",
            "title": "GTLive: TO BUY or NOT TO BUY? | MatPat REACTS to Infomercials!"
        }
    },
    "liveStreamingDetails": {
        "activeLiveChatId": null,
        "actualEndTime": "2018-02-13T01:23:43.000Z",
        "actualStartTime": "2018-02-13T00:06:02.342Z",
        "concurrentViewers": null,
        "scheduledEndTime": null,
        "scheduledStartTime": "2018-02-13T00:00:00.000Z"
    }
}