{
    "etag": "\"j6xRRd8dTPVVptg711_CSPADRfg\/Qa3nRNwh5615I26z2deqo5_Vn2o\"",
    "id": "uOuzIpEKZFk",
    "kind": "youtube#video",
    "snippet": {
        "categoryId": "20",
        "channelId": "UCo_IB5145EVNcf8hw1Kku7w",
        "channelTitle": "The Game Theorists",
        "defaultAudioLanguage": "en",
        "defaultLanguage": null,
        "description": "Click Here for More GTLive Action! \u25ba\u25ba http:\/\/bit.ly\/1Oo7KH9\nI'M SCARED TO OPEN MY EYES!! \u25ba https:\/\/bit.ly\/2Och4oz\nThe SCARIEST Horror Game! Visage\u25ba\u25ba https:\/\/bit.ly\/2QCaww0\n\nToday Theorists, we are running from a new type of animatronic - a terrifying MONKEY! It's trying to keep us from collecting all these soul shards and win our wish. No way!  Try and stop me, Monkey!\n\n#DarkDeception #ScaryGame #HorrorGame #Halloween #MonkeyGame #Animatronics\nSubscribe & hang out with us every day! \u25ba\u25ba http:\/\/bit.ly\/1Oo7KH9\nFollow us on Twitter at @MatPatGT and #GTLive\n\nMore GTLive Videos: \nIT'S PLAY TIME! | Emily Wants to Play Too \u25ba\u25ba http:\/\/bit.ly\/2FLt7Rh\nHARDER Than Getting Over It! \u25ba\u25ba http:\/\/bit.ly\/2EEQpI7\nThe DARK SIDE of Super Mario Odyssey! \u25ba\u25ba http:\/\/bit.ly\/2G2rgLg\nKIDS ARE SO MEAN! Kindergarden (Part 1) \u25ba http:\/\/bit.ly\/2CxizTk\nA New Way To RAGE! Super Mario Party \u25ba https:\/\/bit.ly\/2CucGLq",
        "liveBroadcastContent": "none",
        "publishedAt": "2018-10-10T20:38:34.000Z",
        "tags": [
            "dark deception",
            "dark deception 2",
            "dark deception chapter 1",
            "dark deception chapter 2",
            "dark deception game",
            "dark deception gameplay",
            "dawko dark deception",
            "8 bitryan dark deception",
            "markilpier dark deception",
            "scary game",
            "horror game",
            "dark deception ending",
            "fnaf",
            "fnaf fan games",
            "dark deception jumpscare",
            "jumpscare",
            "fnaf jumpscare",
            "game theorists",
            "game theory",
            "matpat",
            "gtlive",
            "gtlive fnaf",
            "gtlive dark deception",
            "dark",
            "deception"
        ],
        "title": "GTLive: BEWARE the Monkey! | Dark Deception (Scary Game)",
        "thumbnails": {
            "default": {
                "height": 90,
                "url": "https:\/\/i.ytimg.com\/vi\/uOuzIpEKZFk\/default.jpg",
                "width": 120
            },
            "medium": {
                "height": 180,
                "url": "https:\/\/i.ytimg.com\/vi\/uOuzIpEKZFk\/mqdefault.jpg",
                "width": 320
            },
            "high": {
                "height": 360,
                "url": "https:\/\/i.ytimg.com\/vi\/uOuzIpEKZFk\/hqdefault.jpg",
                "width": 480
            }
        },
        "localized": {
            "description": "Click Here for More GTLive Action! \u25ba\u25ba http:\/\/bit.ly\/1Oo7KH9\nI'M SCARED TO OPEN MY EYES!! \u25ba https:\/\/bit.ly\/2Och4oz\nThe SCARIEST Horror Game! Visage\u25ba\u25ba https:\/\/bit.ly\/2QCaww0\n\nToday Theorists, we are running from a new type of animatronic - a terrifying MONKEY! It's trying to keep us from collecting all these soul shards and win our wish. No way!  Try and stop me, Monkey!\n\n#DarkDeception #ScaryGame #HorrorGame #Halloween #MonkeyGame #Animatronics\nSubscribe & hang out with us every day! \u25ba\u25ba http:\/\/bit.ly\/1Oo7KH9\nFollow us on Twitter at @MatPatGT and #GTLive\n\nMore GTLive Videos: \nIT'S PLAY TIME! | Emily Wants to Play Too \u25ba\u25ba http:\/\/bit.ly\/2FLt7Rh\nHARDER Than Getting Over It! \u25ba\u25ba http:\/\/bit.ly\/2EEQpI7\nThe DARK SIDE of Super Mario Odyssey! \u25ba\u25ba http:\/\/bit.ly\/2G2rgLg\nKIDS ARE SO MEAN! Kindergarden (Part 1) \u25ba http:\/\/bit.ly\/2CxizTk\nA New Way To RAGE! Super Mario Party \u25ba https:\/\/bit.ly\/2CucGLq",
            "title": "GTLive: BEWARE the Monkey! | Dark Deception (Scary Game)"
        }
    },
    "liveStreamingDetails": {
        "activeLiveChatId": null,
        "actualEndTime": "2018-10-11T00:09:06.000Z",
        "actualStartTime": "2018-10-10T23:04:11.651Z",
        "concurrentViewers": null,
        "scheduledEndTime": null,
        "scheduledStartTime": "2018-10-10T23:00:00.000Z"
    }
}