{
    "etag": "\"j6xRRd8dTPVVptg711_CSPADRfg\/aCzKua6CqOtiUun9ovHEblg_XmE\"",
    "id": "vBDXEpYybJE",
    "kind": "youtube#video",
    "snippet": {
        "categoryId": "20",
        "channelId": "UCo_IB5145EVNcf8hw1Kku7w",
        "channelTitle": "The Game Theorists",
        "defaultAudioLanguage": "en",
        "defaultLanguage": null,
        "description": "Sayori, NO! | Doki Doki Literature Club! \u25ba\u25ba https:\/\/goo.gl\/D8FjKp\nWatch More GTLive Here! \u25ba\u25ba http:\/\/bit.ly\/1Oo7KH9\nUSE: #GTLIVE and @matpatgt to send us comments & questions!\n\nIt's time to finish DOKI DOKI LITERATURE CLUB! I still like Monika, but she is really starting to Freak Me Out if I'm being honest. Join Steph and I for the final part of this sentient game, and we'll see how much freakier it gets!\n\nSubscribe & hang out with us every day! \u25ba\u25ba http:\/\/bit.ly\/1Oo7KH9\nFollow us on Twitter at @MatPatGT and #GTLive\n\nMore GTLive Videos:\nDating is TERRIFYING! | Doki Doki Lit. Club! \u25ba https:\/\/goo.gl\/edV7RJ\nThe New FNAF Game?! \u25ba\u25ba https:\/\/goo.gl\/TX9opM\nMaster of Moons! | Super Mario Odyssey \u25ba\u25ba https:\/\/goo.gl\/9E7AXX\nThe HUNT IS ON! | Duck Season \u25ba\u25ba https:\/\/goo.gl\/k7DkFC\nCuphead is a DREAM COME TRUE! (Pt 1) \u25ba\u25ba https:\/\/goo.gl\/7qGs2q\nMy Cup Runneth Over! | Cuphead (Pt. 2) \u25ba\u25ba https:\/\/goo.gl\/LLy1vi\nAlice Is No Angel! | Bendy & the Ink Machine \u25ba https:\/\/goo.gl\/68jFV4\nYOGA HURTS! | The Yoga Challenge \u25ba\u25ba https:\/\/goo.gl\/oTJZsq\nMatPat REACTS to YouTubers React! \u25ba\u25ba https:\/\/goo.gl\/3CPnso\n\nDon't have much time but need a quick fix? Check out some of our Must See Moments! Here Are a few to get You Started:\n\nWhy FNAF is Over! | TJoC: Story Mode (Pt.1) \u25ba https:\/\/goo.gl\/Bawy39\nWho's Your DADDY! | Dream Daddy \u25ba\u25ba https:\/\/goo.gl\/eJu12i\nNO RAGE HERE! | World's Easyest Game \u25ba\u25ba https:\/\/goo.gl\/Rc6UN3",
        "liveBroadcastContent": "none",
        "publishedAt": "2017-11-14T21:17:12.000Z",
        "tags": [
            "doki doki literature club",
            "doki doki",
            "doki doki literature club ost",
            "doki doki literature club ending",
            "doki doki literature club game",
            "doki doki literature club song",
            "doki doki song",
            "doki doki monika",
            "doki doki yuri",
            "dating sim",
            "visual novel",
            "doki doki game",
            "doki doki literature club gameplay",
            "walkthrough",
            "lets play",
            "playthrough",
            "doki doki literature club gtlive",
            "gtlive",
            "gt live",
            "matpat",
            "doki doki matpat",
            "monika"
        ],
        "title": "GTLive: Monika and MattyPatty FOREVER! | Doki Doki Literature Club! (Ending)",
        "thumbnails": {
            "default": {
                "height": 90,
                "url": "https:\/\/i.ytimg.com\/vi\/vBDXEpYybJE\/default.jpg",
                "width": 120
            },
            "medium": {
                "height": 180,
                "url": "https:\/\/i.ytimg.com\/vi\/vBDXEpYybJE\/mqdefault.jpg",
                "width": 320
            },
            "high": {
                "height": 360,
                "url": "https:\/\/i.ytimg.com\/vi\/vBDXEpYybJE\/hqdefault.jpg",
                "width": 480
            }
        },
        "localized": {
            "description": "Sayori, NO! | Doki Doki Literature Club! \u25ba\u25ba https:\/\/goo.gl\/D8FjKp\nWatch More GTLive Here! \u25ba\u25ba http:\/\/bit.ly\/1Oo7KH9\nUSE: #GTLIVE and @matpatgt to send us comments & questions!\n\nIt's time to finish DOKI DOKI LITERATURE CLUB! I still like Monika, but she is really starting to Freak Me Out if I'm being honest. Join Steph and I for the final part of this sentient game, and we'll see how much freakier it gets!\n\nSubscribe & hang out with us every day! \u25ba\u25ba http:\/\/bit.ly\/1Oo7KH9\nFollow us on Twitter at @MatPatGT and #GTLive\n\nMore GTLive Videos:\nDating is TERRIFYING! | Doki Doki Lit. Club! \u25ba https:\/\/goo.gl\/edV7RJ\nThe New FNAF Game?! \u25ba\u25ba https:\/\/goo.gl\/TX9opM\nMaster of Moons! | Super Mario Odyssey \u25ba\u25ba https:\/\/goo.gl\/9E7AXX\nThe HUNT IS ON! | Duck Season \u25ba\u25ba https:\/\/goo.gl\/k7DkFC\nCuphead is a DREAM COME TRUE! (Pt 1) \u25ba\u25ba https:\/\/goo.gl\/7qGs2q\nMy Cup Runneth Over! | Cuphead (Pt. 2) \u25ba\u25ba https:\/\/goo.gl\/LLy1vi\nAlice Is No Angel! | Bendy & the Ink Machine \u25ba https:\/\/goo.gl\/68jFV4\nYOGA HURTS! | The Yoga Challenge \u25ba\u25ba https:\/\/goo.gl\/oTJZsq\nMatPat REACTS to YouTubers React! \u25ba\u25ba https:\/\/goo.gl\/3CPnso\n\nDon't have much time but need a quick fix? Check out some of our Must See Moments! Here Are a few to get You Started:\n\nWhy FNAF is Over! | TJoC: Story Mode (Pt.1) \u25ba https:\/\/goo.gl\/Bawy39\nWho's Your DADDY! | Dream Daddy \u25ba\u25ba https:\/\/goo.gl\/eJu12i\nNO RAGE HERE! | World's Easyest Game \u25ba\u25ba https:\/\/goo.gl\/Rc6UN3",
            "title": "GTLive: Monika and MattyPatty FOREVER! | Doki Doki Literature Club! (Ending)"
        }
    },
    "liveStreamingDetails": {
        "activeLiveChatId": null,
        "actualEndTime": "2017-11-15T02:09:32.000Z",
        "actualStartTime": "2017-11-15T00:03:08.971Z",
        "concurrentViewers": null,
        "scheduledEndTime": null,
        "scheduledStartTime": "2017-11-15T00:00:00.000Z"
    }
}