{
    "etag": "\"j6xRRd8dTPVVptg711_CSPADRfg\/IqdpfSvyMQUpOEZQBSxYgsyNNcs\"",
    "id": "w9dTxsbJCIo",
    "kind": "youtube#video",
    "snippet": {
        "categoryId": "20",
        "channelId": "UCAaegDUlb7doIKo0Rc1F08g",
        "channelTitle": "GTLive",
        "defaultAudioLanguage": "en",
        "defaultLanguage": null,
        "description": "SUBSCRIBE for More GTLive Action! \u25ba\u25ba http:\/\/bit.ly\/1Oo7KH9 \n\nToday Team Theorists is facing off against each other in a battle of JackBox Games! Who will come out on top? Join us to find out!\n\nGet Your New Theory Wear Here! \u25ba\u25ba https:\/\/bit.ly\/2N1m7V7\n\nClick Here for More GTLive Action! \u25ba\u25ba http:\/\/bit.ly\/1Oo7KH9  \n\nNeed Royalty Free Music for your Content? Try Epidemic Sound.\nGet Your 30 Day Free Trial \u25ba http:\/\/share.epidemicsound.com\/GTLive\n\n#JackBoxGames #JackBoxPartyPack #PartyGame #partyGames #TriviaMurderParty #JackBox #MatPat\n\nSubscribe & hang out with us every day! \u25ba\u25ba http:\/\/bit.ly\/1Oo7KH9\nFollow us on Twitter at @MatPatGT and #GTLive\n\nMore GTLive Videos: \nFighting Our Friends! Super Mario Party \u25ba https:\/\/bit.ly\/2AOW3qf\nThis RUINS Friendships! Mario Party 10 \u25ba\u25ba https:\/\/bit.ly\/2LTjFhj\nNo Meme is Safe From My Lightsaber! \u25ba https:\/\/bit.ly\/2B7UW5X\nRick and Morty VR FAILS \u25ba https:\/\/bit.ly\/2Dju04N",
        "liveBroadcastContent": "none",
        "publishedAt": "2019-07-19T00:59:05.000Z",
        "tags": [
            "jackbox",
            "jackbox party pack",
            "jack box",
            "jackbox games",
            "jackbox party pack 3",
            "jackbox party pack 5",
            "party games",
            "trivia",
            "trivia murder party",
            "trivia games",
            "game theorists",
            "game theory",
            "gtlive"
        ],
        "title": "You Are Dead WRONG! | Trivia Murder Party (JackBox Games)",
        "thumbnails": {
            "default": {
                "height": 90,
                "url": "https:\/\/i.ytimg.com\/vi\/w9dTxsbJCIo\/default.jpg",
                "width": 120
            },
            "medium": {
                "height": 180,
                "url": "https:\/\/i.ytimg.com\/vi\/w9dTxsbJCIo\/mqdefault.jpg",
                "width": 320
            },
            "high": {
                "height": 360,
                "url": "https:\/\/i.ytimg.com\/vi\/w9dTxsbJCIo\/hqdefault.jpg",
                "width": 480
            }
        },
        "localized": {
            "description": "SUBSCRIBE for More GTLive Action! \u25ba\u25ba http:\/\/bit.ly\/1Oo7KH9 \n\nToday Team Theorists is facing off against each other in a battle of JackBox Games! Who will come out on top? Join us to find out!\n\nGet Your New Theory Wear Here! \u25ba\u25ba https:\/\/bit.ly\/2N1m7V7\n\nClick Here for More GTLive Action! \u25ba\u25ba http:\/\/bit.ly\/1Oo7KH9  \n\nNeed Royalty Free Music for your Content? Try Epidemic Sound.\nGet Your 30 Day Free Trial \u25ba http:\/\/share.epidemicsound.com\/GTLive\n\n#JackBoxGames #JackBoxPartyPack #PartyGame #partyGames #TriviaMurderParty #JackBox #MatPat\n\nSubscribe & hang out with us every day! \u25ba\u25ba http:\/\/bit.ly\/1Oo7KH9\nFollow us on Twitter at @MatPatGT and #GTLive\n\nMore GTLive Videos: \nFighting Our Friends! Super Mario Party \u25ba https:\/\/bit.ly\/2AOW3qf\nThis RUINS Friendships! Mario Party 10 \u25ba\u25ba https:\/\/bit.ly\/2LTjFhj\nNo Meme is Safe From My Lightsaber! \u25ba https:\/\/bit.ly\/2B7UW5X\nRick and Morty VR FAILS \u25ba https:\/\/bit.ly\/2Dju04N",
            "title": "You Are Dead WRONG! | Trivia Murder Party (JackBox Games)"
        }
    },
    "topicDetails": {
        "relevantTopicIds": [
            "\/m\/025zzc",
            "\/m\/0bzvm2",
            "\/m\/0bzvm2"
        ],
        "topicCategories": [
            "https:\/\/en.wikipedia.org\/wiki\/Video_game_culture",
            "https:\/\/en.wikipedia.org\/wiki\/Action_game"
        ],
        "topicIds": null
    },
    "liveStreamingDetails": {
        "activeLiveChatId": null,
        "actualEndTime": "2019-07-19T00:22:09.000Z",
        "actualStartTime": "2019-07-18T23:00:20.218Z",
        "concurrentViewers": null,
        "scheduledEndTime": null,
        "scheduledStartTime": "2019-07-18T23:00:00.000Z"
    }
}