{
    "etag": "\"j6xRRd8dTPVVptg711_CSPADRfg\/oH_aqIIjc9nnyZIVYgzMqheceps\"",
    "id": "XBmr1gnk76w",
    "kind": "youtube#video",
    "snippet": {
        "categoryId": "20",
        "channelId": "UCAaegDUlb7doIKo0Rc1F08g",
        "channelTitle": "GTLive",
        "defaultAudioLanguage": "en-US",
        "defaultLanguage": null,
        "description": "Subscribe for more GTLive action! \u25ba\u25bahttp:\/\/bit.ly\/1Oo7KH9 \nLife is Strange (Part 1)  \u25ba\u25ba http:\/\/bit.ly\/20UoKIx\nToo HOT for YOUtube! - Pico Sim Date \u25ba\u25ba http:\/\/bit.ly\/1LBhQEK\n\nThe murderer is finally revealed - as we find ourselves in over our heads! Perhaps we should have avoided the End of Days Pool Party altogether. Now we are forced to relive the worst day of our lives over and over again. \n\nSubscribe & hang out with us every day! \u25ba\u25ba http:\/\/bit.ly\/1Oo7KH9\nFollow us on Twitter at @MatPatGT and #GTLive\n\nEven More GTLive\nOversexualize Me! - Netflix & Chill \u25ba\u25ba http:\/\/bit.ly\/22zbE4k\nFive Nights at Candy's - Sad Puppet is Sad \u25ba http:\/\/bit.ly\/1U1zzYy\nMatPat vs The Bomb - Keep Talking... \u25ba\u25ba http:\/\/bit.ly\/1pFoVdD\n\nDon't have much time but need a quick fix? Check out some of our highlight episodes for hilarious moments from our live streams. Here are a few to get you started.\n\nHiLite: Trapped in the UNCANNY VALLEY \u25ba http:\/\/bit.ly\/1QGET23\nHiLite: Flappy Mario Maker? JUST DO IT!\u25ba http:\/\/bit.ly\/1OOyOyL\nHiLite: FNAF Theorists Surprised By Scott! \u25bahttp:\/\/bit.ly\/1Jrlm3i",
        "liveBroadcastContent": "none",
        "publishedAt": "2016-03-21T17:30:55.000Z",
        "tags": [
            "walkthrough",
            "playthrough",
            "life is strange",
            "lets play",
            "life is strange game",
            "choice",
            "choice based game",
            "RPG",
            "gameplay",
            "gtlive",
            "gt live",
            "game theory live",
            "matpat",
            "matthew patrick",
            "matthewpatrick13",
            "End of world",
            "party",
            "rave",
            "pool party",
            "sexy",
            "murderer uncovered",
            "killer",
            "killer revealed"
        ],
        "title": "Life Is Strange - SEX, DRUGS, & Attempted MURDER! (Part 9)",
        "thumbnails": {
            "default": {
                "height": 90,
                "url": "https:\/\/i.ytimg.com\/vi\/XBmr1gnk76w\/default.jpg",
                "width": 120
            },
            "medium": {
                "height": 180,
                "url": "https:\/\/i.ytimg.com\/vi\/XBmr1gnk76w\/mqdefault.jpg",
                "width": 320
            },
            "high": {
                "height": 360,
                "url": "https:\/\/i.ytimg.com\/vi\/XBmr1gnk76w\/hqdefault.jpg",
                "width": 480
            },
            "standard": {
                "height": 480,
                "url": "https:\/\/i.ytimg.com\/vi\/XBmr1gnk76w\/sddefault.jpg",
                "width": 640
            },
            "maxres": {
                "height": 720,
                "url": "https:\/\/i.ytimg.com\/vi\/XBmr1gnk76w\/maxresdefault.jpg",
                "width": 1280
            }
        },
        "localized": {
            "description": "Subscribe for more GTLive action! \u25ba\u25bahttp:\/\/bit.ly\/1Oo7KH9 \nLife is Strange (Part 1)  \u25ba\u25ba http:\/\/bit.ly\/20UoKIx\nToo HOT for YOUtube! - Pico Sim Date \u25ba\u25ba http:\/\/bit.ly\/1LBhQEK\n\nThe murderer is finally revealed - as we find ourselves in over our heads! Perhaps we should have avoided the End of Days Pool Party altogether. Now we are forced to relive the worst day of our lives over and over again. \n\nSubscribe & hang out with us every day! \u25ba\u25ba http:\/\/bit.ly\/1Oo7KH9\nFollow us on Twitter at @MatPatGT and #GTLive\n\nEven More GTLive\nOversexualize Me! - Netflix & Chill \u25ba\u25ba http:\/\/bit.ly\/22zbE4k\nFive Nights at Candy's - Sad Puppet is Sad \u25ba http:\/\/bit.ly\/1U1zzYy\nMatPat vs The Bomb - Keep Talking... \u25ba\u25ba http:\/\/bit.ly\/1pFoVdD\n\nDon't have much time but need a quick fix? Check out some of our highlight episodes for hilarious moments from our live streams. Here are a few to get you started.\n\nHiLite: Trapped in the UNCANNY VALLEY \u25ba http:\/\/bit.ly\/1QGET23\nHiLite: Flappy Mario Maker? JUST DO IT!\u25ba http:\/\/bit.ly\/1OOyOyL\nHiLite: FNAF Theorists Surprised By Scott! \u25bahttp:\/\/bit.ly\/1Jrlm3i",
            "title": "Life Is Strange - SEX, DRUGS, & Attempted MURDER! (Part 9)"
        }
    },
    "topicDetails": {
        "relevantTopicIds": [
            "\/m\/02jjt",
            "\/m\/0f2f9",
            "\/m\/02jjt",
            "\/m\/0f2f9",
            "\/m\/0f2f9"
        ],
        "topicCategories": [
            "https:\/\/en.wikipedia.org\/wiki\/Entertainment",
            "https:\/\/en.wikipedia.org\/wiki\/Television_program"
        ],
        "topicIds": null
    }
}