{
    "etag": "\"j6xRRd8dTPVVptg711_CSPADRfg\/64qEm4pU6DtdEmR1p5OzLVvSfPc\"",
    "id": "ZVlWjJlqDYU",
    "kind": "youtube#video",
    "snippet": {
        "categoryId": "20",
        "channelId": "UCAaegDUlb7doIKo0Rc1F08g",
        "channelTitle": "GTLive",
        "defaultAudioLanguage": "en-US",
        "defaultLanguage": "en",
        "description": "Subscribe for more GTLive action! \u25ba\u25ba http:\/\/bit.ly\/1Oo7KH9 \nMissed Part 1? Watch it Now \u25ba\u25ba http:\/\/bit.ly\/2ePe5R0\nBlowing Up Springtrap in TJOC! \u25ba http:\/\/bit.ly\/2fuuner\nWe MURDERED Hello Neighbor \u25ba http:\/\/bit.ly\/2fymWTI\n\nWe're putting the burning questions to bed as we solve the mystery behind Layers of Fear. Why am I trapped in this Hellish nightmare? Did my wife die in a fire? Did I kill my family? Will I seek redemption? We find out today!\n\nSubscribe & hang out with us every day! \u25ba\u25ba http:\/\/bit.ly\/1Oo7KH9\nFollow us on Twitter at @MatPatGT and #GTLive\n\nMore GTLive Videos:\nTORTURED by One Night At FLUMPTY'S!\u25ba\u25ba http:\/\/bit.ly\/20VUcEs\nSad Puppet is Sad! - FNAC Part 1 \u25ba\u25ba http:\/\/bit.ly\/1U8Xs0I\nWe FIGHT W.D. Gaster! \u25ba\u25ba http:\/\/bit.ly\/1N6XCTK\nWe KILL Chara! \u25ba\u25ba\u25ba http:\/\/bit.ly\/1qMyBmU\n\nDon't have much time but need a quick fix? Check out some of our highlight episodes for hilarious moments from our live streams. Here are a few to get you started.\n\nHiLite: Flappy Mario Maker? JUST DO IT! \u25ba http:\/\/bit.ly\/1Oq8GvE\nHiLite: FNAF Theorists Surprised By Scott! \u25ba http:\/\/bit.ly\/1Jrlm3i\nHiLite: Mega Man Marshmallow Challenge! \u25ba http:\/\/bit.ly\/1OHe3kb\n\nThanks to David Keller for allowing us use of his sound FX:\nhttp:\/\/consumingfireartisticcreations.weebly.com\/",
        "liveBroadcastContent": "none",
        "publishedAt": "2016-11-21T19:11:17.000Z",
        "tags": [
            "layers of fear",
            "layers of fear game",
            "layers of fear gameplay",
            "walkthrough",
            "horror",
            "horror game",
            "scary game",
            "scare",
            "scary",
            "lets play",
            "playthrough",
            "jumpscare",
            "creepy",
            "halloween",
            "scream",
            "scared",
            "reactions",
            "gameplay",
            "survival",
            "game theory",
            "gtlive",
            "game theory live",
            "game theory matpat",
            "matpat fan game"
        ],
        "title": "Solving My HORRIBLE Mystery! | Layers of Fear Ending (Part 2 of 2)",
        "thumbnails": {
            "default": {
                "height": 90,
                "url": "https:\/\/i.ytimg.com\/vi\/ZVlWjJlqDYU\/default.jpg",
                "width": 120
            },
            "medium": {
                "height": 180,
                "url": "https:\/\/i.ytimg.com\/vi\/ZVlWjJlqDYU\/mqdefault.jpg",
                "width": 320
            },
            "high": {
                "height": 360,
                "url": "https:\/\/i.ytimg.com\/vi\/ZVlWjJlqDYU\/hqdefault.jpg",
                "width": 480
            },
            "standard": {
                "height": 480,
                "url": "https:\/\/i.ytimg.com\/vi\/ZVlWjJlqDYU\/sddefault.jpg",
                "width": 640
            },
            "maxres": {
                "height": 720,
                "url": "https:\/\/i.ytimg.com\/vi\/ZVlWjJlqDYU\/maxresdefault.jpg",
                "width": 1280
            }
        },
        "localized": {
            "description": "Subscribe for more GTLive action! \u25ba\u25ba http:\/\/bit.ly\/1Oo7KH9 \nMissed Part 1? Watch it Now \u25ba\u25ba http:\/\/bit.ly\/2ePe5R0\nBlowing Up Springtrap in TJOC! \u25ba http:\/\/bit.ly\/2fuuner\nWe MURDERED Hello Neighbor \u25ba http:\/\/bit.ly\/2fymWTI\n\nWe're putting the burning questions to bed as we solve the mystery behind Layers of Fear. Why am I trapped in this Hellish nightmare? Did my wife die in a fire? Did I kill my family? Will I seek redemption? We find out today!\n\nSubscribe & hang out with us every day! \u25ba\u25ba http:\/\/bit.ly\/1Oo7KH9\nFollow us on Twitter at @MatPatGT and #GTLive\n\nMore GTLive Videos:\nTORTURED by One Night At FLUMPTY'S!\u25ba\u25ba http:\/\/bit.ly\/20VUcEs\nSad Puppet is Sad! - FNAC Part 1 \u25ba\u25ba http:\/\/bit.ly\/1U8Xs0I\nWe FIGHT W.D. Gaster! \u25ba\u25ba http:\/\/bit.ly\/1N6XCTK\nWe KILL Chara! \u25ba\u25ba\u25ba http:\/\/bit.ly\/1qMyBmU\n\nDon't have much time but need a quick fix? Check out some of our highlight episodes for hilarious moments from our live streams. Here are a few to get you started.\n\nHiLite: Flappy Mario Maker? JUST DO IT! \u25ba http:\/\/bit.ly\/1Oq8GvE\nHiLite: FNAF Theorists Surprised By Scott! \u25ba http:\/\/bit.ly\/1Jrlm3i\nHiLite: Mega Man Marshmallow Challenge! \u25ba http:\/\/bit.ly\/1OHe3kb\n\nThanks to David Keller for allowing us use of his sound FX:\nhttp:\/\/consumingfireartisticcreations.weebly.com\/",
            "title": "Solving My HORRIBLE Mystery! | Layers of Fear Ending (Part 2 of 2)"
        }
    },
    "topicDetails": {
        "relevantTopicIds": [
            "\/m\/0bzvm2",
            "\/m\/025zzc",
            "\/m\/0bzvm2",
            "\/m\/025zzc"
        ],
        "topicCategories": [
            "https:\/\/en.wikipedia.org\/wiki\/Action_game",
            "https:\/\/en.wikipedia.org\/wiki\/Video_game_culture"
        ],
        "topicIds": null
    }
}